anvaad_py/__init__.py
anvaad_py/alphabetize.py
anvaad_py/ascii.py
anvaad_py/firstLetters.py
anvaad_py/mainLetters.py
anvaad_py/unicode.py
anvaad_py-0.0.7.dist-info/LICENSE
anvaad_py-0.0.7.dist-info/METADATA
anvaad_py-0.0.7.dist-info/WHEEL
anvaad_py-0.0.7.dist-info/top_level.txt
anvaad_py-0.0.7.dist-info/RECORD
