Metadata-Version: 2.1
Name: anvaad-py
Version: 0.0.7
Summary: A Python utility to translit gurmukhi, and convert it between ascii to unicode with ease! (Python version of anvaad-js)
Author-email: "0xharkirat (Harkirat Singh)" <info.sandhukirat23@gmail.com>
Project-URL: Homepage, https://github.com/0xharkirat/anvaad-py
Project-URL: Bug Tracker, https://github.com/0xharkirat/anvaad-py
Classifier: Programming Language :: Python :: 3
Classifier: License :: OSI Approved :: MIT License
Classifier: Operating System :: OS Independent
Requires-Python: >=3.7
License-File: LICENSE
